setup.py
lv_probability/Binomialdistribution.py
lv_probability/Gaussiandistribution.py
lv_probability/Generaldistribution.py
lv_probability/__init__.py
lv_probability.egg-info/PKG-INFO
lv_probability.egg-info/SOURCES.txt
lv_probability.egg-info/dependency_links.txt
lv_probability.egg-info/not-zip-safe
lv_probability.egg-info/top_level.txt